etherscan/__init__.py
etherscan/accounts.py
etherscan/client.py
etherscan/contracts.py
etherscan/proxies.py
etherscan/stats.py
etherscan/tokens.py
examples/__init__.py
examples/accounts/__init__.py
examples/accounts/get_all_blocks_mined.py
examples/accounts/get_all_transactions.py
examples/accounts/get_balance.py
examples/accounts/get_balance_multi.py
examples/accounts/get_blocks_mined.py
examples/accounts/get_transaction_page.py
examples/accounts/get_transaction_page_erc20.py
examples/stats/__init__.py
examples/stats/get_ether_last_price.py
examples/stats/get_total_ether_supply.py
examples/tokens/__init__.py
examples/tokens/get_token_balance.py
examples/tokens/get_total_supply.py
py_etherscan_api-0.8.0.dist-info/LICENSE
py_etherscan_api-0.8.0.dist-info/METADATA
py_etherscan_api-0.8.0.dist-info/WHEEL
py_etherscan_api-0.8.0.dist-info/top_level.txt
py_etherscan_api-0.8.0.dist-info/RECORD
